{
    "produtos": [
        {
            "id": "1",
            "nome": "Produto A",
            "descricao": "Descrição do Produto A.",
            "preco": 79.00,
            "tipo": "camiseta",
            "tamanhos": {
                "P": 1,
                "M": 1,
                "G": 1,
                "GG": 1,
                "G1": 1,
                "G2": 1,
                "G3": 1,
                "G4": 1
            },
            "imagem": "/public/camiseta1.svg"
        },
        {
            "id": "2",
            "nome": "Produto B",
            "descricao": "Descrição do Produto B.",
            "preco": 79.00,
            "tipo": "camiseta",
            "tamanhos": {
                "P": 1,
                "M": 1,
                "G": 1,
                "GG": 1,
                "G1": 1,
                "G2": 1,
                "G3": 1,
                "G4": 1
            },
            "imagem": "/public/camiseta1.svg"
        },
        {
            "id": "3",
            "nome": "Produto C",
            "descricao": "Descrição do Produto C.",
            "preco": 79.00,
            "tipo": "camiseta",
            "tamanhos": {
                "P": 1,
                "M": 1,
                "G": 1,
                "GG": 1,
                "G1": 1,
                "G2": 1,
                "G3": 1,
                "G4": 1
            },
            "imagem": "/public/camiseta1.svg"
        },
        {
            "id": "4",
            "nome": "Produto D",
            "descricao": "Descrição do Produto D.",
            "preco": 79.00,
            "tipo": "camiseta",
            "tamanhos": {
                "P": 1,
                "M": 1,
                "G": 1,
                "GG": 1,
                "G1": 1,
                "G2": 1,
                "G3": 1,
                "G4": 1
            },
            "imagem": "/public/camiseta1.svg"
        }
    ]
}